mcputil/__init__.py
mcputil/client.py
mcputil/func.py
mcputil/tool.py
mcputil/types.py
mcputil-0.5.0.dist-info/METADATA
mcputil-0.5.0.dist-info/WHEEL
mcputil-0.5.0.dist-info/licenses/LICENSE
mcputil-0.5.0.dist-info/RECORD
