Metadata-Version: 2.4
Name: mcputil
Version: 0.5.0
Summary: A lightweight library that converts MCP tools into Python tools (function-like objects).
Author-email: RussellLuo <luopeng.he@gmail.com>
License-File: LICENSE
Requires-Python: >=3.10
Requires-Dist: aiorwlock>=1.5.0
Requires-Dist: jsonschema>=4.25.1
Requires-Dist: mcp>=1.19.0
